nhl_logo_scraper/__init__.py
nhl_logo_scraper/cli.py
nhl_logo_scraper/utils.py
nhl_logo_scraper/commands/__init__.py
nhl_logo_scraper/commands/base.py
nhl_logo_scraper/commands/clean.py
nhl_logo_scraper/commands/scrape.py
nhl_logo_scraper-1.1.0.dist-info/DESCRIPTION.rst
nhl_logo_scraper-1.1.0.dist-info/METADATA
nhl_logo_scraper-1.1.0.dist-info/RECORD
nhl_logo_scraper-1.1.0.dist-info/WHEEL
nhl_logo_scraper-1.1.0.dist-info/entry_points.txt
nhl_logo_scraper-1.1.0.dist-info/metadata.json
nhl_logo_scraper-1.1.0.dist-info/top_level.txt
