Metadata-Version: 2.0
Name: nhl-logo-scraper
Version: 1.1.0
Summary: Scrape logos for all NHL teams
Home-page: https://github.com/blindman/nhl-logo-scraper
Author: Jon Heller
Author-email: jon.heller02@gmail.com
License: MIT
Keywords: cli
Platform: UNKNOWN
Classifier: Programming Language :: Python :: 3.5
Classifier: Programming Language :: Python :: 3.6
Classifier: Environment :: Console
Classifier: Intended Audience :: Developers
Classifier: Topic :: Utilities
Classifier: License :: OSI Approved :: MIT License
Requires-Dist: cairosvg
Requires-Dist: cssselect
Requires-Dist: cssutils
Requires-Dist: docopt
Requires-Dist: lxml
Requires-Dist: requests
Provides-Extra: test
Requires-Dist: codecov; extra == 'test'
Requires-Dist: coverage; extra == 'test'
Requires-Dist: pytest; extra == 'test'
Requires-Dist: pytest-cov; extra == 'test'
